freefang_qt/__init__.py
freefang_qt/data.py
freefang_qt/game_creation.py
freefang_qt/game_join.py
freefang_qt/gameloop.py
freefang_qt/main.py
freefang_qt/net.py
freefang_qt/packets.py
freefang_qt/utils.py
freefang_qt/qml/ActionButton.qml
freefang_qt/qml/Create_Game.qml
freefang_qt/qml/Cupidinfatuate.qml
freefang_qt/qml/Game_UI.qml
freefang_qt/qml/HunterKill.qml
freefang_qt/qml/Join_Game.qml
freefang_qt/qml/ProtectorProtect.qml
freefang_qt/qml/SeerReveal.qml
freefang_qt/qml/Vote.qml
freefang_qt/qml/Werewolfvote.qml
freefang_qt/qml/Witch_kill.qml
freefang_qt/qml/Witch_revive.qml
freefang_qt/qml/Witchpassturnbtn.qml
freefang_qt/qml/main.qml
freefang_qt-0.2.0.dist-info/LICENSE
freefang_qt-0.2.0.dist-info/METADATA
freefang_qt-0.2.0.dist-info/WHEEL
freefang_qt-0.2.0.dist-info/entry_points.txt
freefang_qt-0.2.0.dist-info/top_level.txt
freefang_qt-0.2.0.dist-info/RECORD
