Metadata-Version: 2.1
Name: freefang-qt
Version: 0.2.0
Summary: A PySide client for the FreeFang werewolf gameserver.
Author-email: Solaris <iusegentoobtw@protonmail.com>
Project-URL: Homepage, https://github.com/FreeFangGame/freefang-qt
Project-URL: Bug Tracker, https://github.com/FreeFangGame/freefang-qt/issues
Classifier: Programming Language :: Python :: 3
Classifier: License :: OSI Approved :: GNU General Public License v3 (GPLv3)
Classifier: Operating System :: OS Independent
License-File: LICENSE
Requires-Dist: pyside6
